aiokalshi/__init__.py
aiokalshi/client.py
aiokalshi/models/__init__.py
aiokalshi/models/events.py
aiokalshi/models/markets.py
aiokalshi/models/series.py
aiokalshi/resources/__init__.py
aiokalshi/resources/events.py
aiokalshi/resources/markets.py
aiokalshi/resources/series.py
aiokalshi-0.1.0.dist-info/METADATA
aiokalshi-0.1.0.dist-info/WHEEL
aiokalshi-0.1.0.dist-info/top_level.txt
aiokalshi-0.1.0.dist-info/RECORD
