Metadata-Version: 2.4
Name: aiokalshi
Version: 0.1.0
Summary: An asyncio-native Kalshi API.
Requires-Python: >=3.12
Requires-Dist: httpx>=0.28.1
Requires-Dist: pydantic>=2.12.0
Requires-Dist: structlog>=25.4.0
Requires-Dist: yarl>=1.22.0
